{"Strats":
    {
        "Info":"These strats are from Kyrrone's strat guide on SRC. Find more details for these strats at this link: https://www.speedrun.com/balan_wonderworld/guide/u7lny",
        "General":
        {           
            "Float Mash":"By mashing the action button, you can get more distance with certain costumes that enhance your jump.\nThis works with:\n- Soaring Sheep\n- Frost Fairy"            
        },
        "1-1":
        {
            "Mirror Skip":"https://youtu.be/G2OnbhvRjwI",
            "Pumpkin Jump":"https://youtu.be/qjmApSbbdCs"
        },
        "1-2":
        {
            "Level Skip":"https://youtu.be/DcBrRfVJsx8",
            "Ball Puzzle Skip":"https://youtu.be/f8Y6KrlRrgg",
            "Fast Mini Boss":"https://youtu.be/nFDxj-sSXCo",
            "Faster Mini Boss":"https://youtu.be/qQg_MJ1DkaY"
        },
        "2-1":
        {
            "First Switch Skip":"https://youtu.be/Uo5EcYo21KU",
            "Second Swith Skip":"https://youtu.be/uK3hGf6e93w",
            "Gate Skip":"https://youtu.be/cAMqKG6qScI"
        },
        "2-2":
        {
            "Early Double Jumper":"https://youtu.be/wjZ5f75e8vc",
            "Mini Boss Skip":"https://youtu.be/uwR6M2TZllY"
        },
        "3-1":
        {
            "Web Jump":"https://youtu.be/B7g2v7Yr0m4",
            "Mushroom Skip":"https://youtu.be/OTc3EmgXUpQ"
        },
        "3-2":
        {
            "Mini Boss Skip":"https://youtu.be/N4YLivRzKfs"
        },
        "4-1":
        {
            "GPT Skip":"https://youtu.be/IaFQ-yLjjL8",
            "Mirror Coyote":"https://youtu.be/MjI61q9knio",
            "Mini Boss Skip":"https://youtu.be/Afo6dNhUJ3w"
        },
        "4-2":
        {
            "Level Skip":"https://youtu.be/qx2tijjj5BA"
        },
        "5-1":
        {
            "Mini Boss Skip":"https://youtu.be/rL1o8j2Gn3U"
        }
    }
}

